<?xml version="1.0" encoding="UTF-8" ?>

<configuration>
  <appender name="ROLLING" class="ch.qos.logback.core.rolling.RollingFileAppender">
    <file>${logger.logfile.path}</file>
    <rollingPolicy class="ch.qos.logback.core.rolling.FixedWindowRollingPolicy">
      <fileNamePattern>${storm.home}/logs/${logger.logfile.name}.%i</fileNamePattern>
      <minIndex>1</minIndex>
      <maxIndex>9</maxIndex>
    </rollingPolicy>

    <triggeringPolicy class="ch.qos.logback.core.rolling.SizeBasedTriggeringPolicy">
      <maxFileSize>100MB</maxFileSize>
    </triggeringPolicy>

    <encoder>
      <pattern>%d{yyyy-MM-dd HH:mm:ss} %c{1} [%p] %m%n</pattern>
    </encoder>
  </appender>

  <root>
    <level value ="INFO"/>
    <appender-ref ref="ROLLING" />
  </root>  
</configuration>
